vsjet/__init__.py
vsjet/__main__.py
vsjet/_metadata.py
vsjet/init.py
vsjet-3.4.3.dist-info/LICENSE
vsjet-3.4.3.dist-info/METADATA
vsjet-3.4.3.dist-info/WHEEL
vsjet-3.4.3.dist-info/entry_points.txt
vsjet-3.4.3.dist-info/top_level.txt
vsjet-3.4.3.dist-info/RECORD
