Metadata-Version: 2.2
Name: vsjet
Version: 3.4.3
Summary: VapourSynth packages from JET
Author: Setsugen no ao
Author-email: setsugen@setsugen.dev
Maintainer: Setsugen no ao
Maintainer-email: setsugen@setsugen.dev
Project-URL: Source Code, https://github.com/Jaded-Encoding-Thaumaturgy
Project-URL: Contact, https://discord.gg/XTpc6Fa9eB
Classifier: Programming Language :: Python :: 3
Classifier: License :: OSI Approved :: MIT License
Classifier: Operating System :: OS Independent
Requires-Python: >=3.12
License-File: LICENSE
Requires-Dist: VapourSynth>=68
Requires-Dist: stgpytools>=1.2.0
Requires-Dist: vstools==3.3.4
Requires-Dist: vspyplugin==1.4.3
Requires-Dist: vskernels==3.3.1
Requires-Dist: vsexprtools==1.7.1
Requires-Dist: vsrgtools==1.8.1
Requires-Dist: vsmasktools==1.3.2
Requires-Dist: vsaa==1.11.2
Requires-Dist: vsscale==2.2.1
Requires-Dist: vsdenoise==2.7.1
Requires-Dist: vsdehalo==1.9.2
Requires-Dist: vsdeband==1.2.2
Requires-Dist: vsdeinterlace==0.8.1
Requires-Dist: vssource==0.11.2
Requires-Dist: vspreview==0.10.1
Dynamic: author
Dynamic: author-email
Dynamic: classifier
Dynamic: description
Dynamic: description-content-type
Dynamic: maintainer
Dynamic: maintainer-email
Dynamic: project-url
Dynamic: requires-dist
Dynamic: requires-python
Dynamic: summary
